pyjoker/__init__.py
pyjoker/categories.py
pyjoker/jokes.csv
pyjoker/jokes.py
pyjoker-0.1.0.dist-info/LICENSE
pyjoker-0.1.0.dist-info/METADATA
pyjoker-0.1.0.dist-info/WHEEL
pyjoker-0.1.0.dist-info/top_level.txt
pyjoker-0.1.0.dist-info/RECORD
