Metadata-Version: 2.1
Name: pyjoker
Version: 0.1.0
Summary: A Python package for categorized one-liner jokes.
Home-page: https://github.com/ashainp
Author: Ashain Perera
Author-email: ashainperera95@gmail.com
License: UNKNOWN
Platform: UNKNOWN
Classifier: Programming Language :: Python :: 3
Classifier: License :: OSI Approved :: MIT License
Classifier: Operating System :: OS Independent
Requires-Python: >=3.6
Requires-Dist: pandas
